{
 "response": "```json\n{\n  \"target\": \"contract(service_agreement)\",\n  \"candidates\": [\n    \"df_contract(service_agreement):  => contract(service_agreement)\",\n    \"df_legal_document(nda):  => legal_document(nda)\",\n    \"df_legal_document(clean_water_act):  => legal_document(clean_water_act)\",\n    \"df_statute(civil_rights_act):  => statute(civil_rights_act)\",\n    \"df_statute(ada):  => statute(ada)\",\n    \"df_legal_document(employment_contract):  => legal_document(employment_contract)\"\n  ]\n}\n```",
 "at": null,
 "meta": {
  "system": "Extract from the text, VERBATIM. Reply ONLY JSON: {\"target\":\"<the underivable statement>\",\"candidates\":[\"<entry as writt",
  "user": "A knowledge base is missing exactly one entry. Because of that gap, the statement \"contract(service_agreement)\" cannot be derived. Exactly one of the following candidate entries fills the gap:\n  (1) d"
 }
}