{
 "response": "The problem states that the knowledge base is missing one entry, and because of that, \"legal_document(ferpa)\" cannot be derived. We need to find the entry that, when added, would allow us to derive \"legal_document(ferpa)\".\n\nLet's analyze each candidate:\n\n*   **(1) df_legal_document(ferpa):  => legal_document(ferpa)**: This directly states that `ferpa` is a legal document. Adding this would allow us to derive `legal_document(ferpa)`.\n*   **(2) df_legal_document(service_agreement):  => legal_document(service_agreement)**: This relates `service_agreement` to being a legal document, but doesn't help with `ferpa`.\n*   **(3) df_statute(ada):  => statute(ada)**: This relates `ada` to being a statute, not a legal document.\n*   **(4) df_legal_action(subpoena):  => legal_action(subpoena)**: This relates `subpoena` to being a legal action, not a legal document.\n*   **(5) df_legal_document(partnership_agreement):  => legal_document(partnership_agreement)**: This relates `partnership_agreement` to being a legal document, but doesn't help with `ferpa`.\n*   **(6) df_statute(ferpa):  => statute(ferpa)**: This relates `ferpa` to being a statute, but not a legal document.\n\nOnly option (1) directly provides the information needed to derive \"legal_document(ferpa)\".\n\nTherefore, the correct answer is (1).",
 "at": null,
 "meta": {
  "system": "Extract from the text, VERBATIM. Reply ONLY JSON: {\"target\":\"<the underivable statement>\",\"candidates\":[\"<entry as writt",
  "user": "A knowledge base is missing exactly one entry. Because of that gap, the statement \"legal_document(ferpa)\" cannot be derived. Exactly one of the following candidate entries fills the gap:\n  (1) df_lega"
 }
}