{
 "response": "Okay, let's analyze the situation and craft an exception rule.\n\n**Understanding the Problem**\n\nThe rules state that minors *always* lack contractual capacity.  The observed anomaly is that Alex, a minor, *does* lack contractual capacity (which is what the rule *should* predict, but we're looking for an exception to explain *why* it's happening).  We need a rule that explains this without disrupting the general rule for other minors or the rule for adults.\n\n**Reasoning and Proposed Exception Rule**\n\nThe core issue is that the general rule `r_minor_cap` is too absolute.  It doesn't account for situations where a minor's contractual capacity might be specifically limited *beyond* the general lack of capacity.  A possible explanation is that Alex is under a guardianship or conservatorship that further restricts their ability to enter into contracts.\n\nTherefore, the exception rule should focus on this specific circumstance.\n\n**Proposed Exception Rule:**\n\n`~> minor(X) & under_guardianship(X) => lacks_contractual_capacity(X)`\n\n**Explanation:**\n\n*   `~>`:  This indicates an exception to a general rule.\n*   `minor(X)`:  This ensures the rule only applies to minors.\n*   `&`:  This combines the two conditions.\n*   `under_guardianship(X)`: This is the *specific* condition that triggers the exception.  It means Alex is under a legal guardianship or conservatorship.\n*   `=> lacks_contractual_capacity(X)`: This states that if a person is a minor *and* under guardianship, they lack contractual capacity.\n\n**Why this is a good solution:**\n\n*   **Addresses the Anomaly:** It directly explains why Alex lacks contractual capacity, given that they are a minor.\n*   **Specificity:** It's as specific as possible, targeting a particular legal circumstance (guardianship) rather than a broad generalization.\n*   **Doesn't Break Other Expectations:**\n    *   It doesn't contradict `r_minor_cap` in general. It *adds* a specific condition under which the lack of capacity is reinforced.\n    *   It doesn't affect `r_adult_bound`.\n    *   It doesn't affect the general rule for minors who *aren't* under guardianship.\n*   **Plausible:**  Guardianships and conservatorships are legal mechanisms that routinely restrict a minor's ability to enter into contracts.\n\n**Important Note:**  To fully implement this, you'd need to add a fact: `under_guardianship(alex)`.  Without that fact, the exception rule wouldn't be triggered.\n",
 "at": null,
 "meta": {
  "system": "Pick the single best exception rule. Candidates:\nd_emancipated: court_emancipated(X) ~> ~lacks_contractual_capacity(X)\nd",
  "user": "Facts: adult(taylor), minor(alex), minor(sam).\nGeneral rules (=> means \"normally implies\"): r_minor_cap: minor(X) => lacks_contractual_capacity(X); r_adult_bound: adult(X) => bound_by_contract(X); r_p"
 }
}