{
 "response": "\n\n{\"candidates\":[\"d_ostrich: ostrich(X) ~> ~flies(X)\", \"d_ostrich_broad: bird(X) ~> ~flies(X)\"]}",
 "at": null,
 "meta": {
  "system": "Extract each candidate exception rule as JSON. For the anomaly \"flies(obi)\", list the candidate rules. Reply ONLY JSON: ",
  "user": "Facts: bird(obi), bird(tweety), ostrich(obi), sparrow(tweety).\nGeneral rules (=> means \"normally implies\"): r_flies: bird(X) => flies(X); r_feathers: bird(X) => has_feathers(X); r_warm: bird(X) => war"
 }
}