{
 "response": "aquatic\n\nA red trout is a freshwater fish that naturally lives in water environments. The fish tank would be the appropriate habitat for a red trout, as it provides the aquatic environment the fish needs to survive. The bird cage and reptile house are not suitable for fish - they are designed for aerial and terrestrial animals respectively.",
 "at": null,
 "meta": {
  "system": "Answer the puzzle with EXACTLY one of: aquatic | aerial | terrestrial | none.",
  "user": "You're holding a red trout. Where would you place it among these three habitats: the fish tank, the bird cage, or the reptile house? Which option would you choose?"
 }
}