{
 "response": "{\"object\":{\"kind\":\"sphere\",\"category\":\"\",\"condition\":\"soggy\",\"color\":\"green\",\"size\":\"\"},\"holes\":[{\"name\":\"five-pointed star\",\"size\":\"\"},{\"name\":\"square\",\"size\":\"\"},{\"name\":\"circle\",\"size\":\"\"}]}",
 "at": null,
 "meta": {
  "system": "You extract the structure of a placement puzzle. Copy the words AS WRITTEN in the text (do not normalize). Reply ONLY JS",
  "user": "Imagine you have a soggy, green sphere. You need to place it into one of three openings: a five-pointed star, a perfect square, or a circle. Which hole should you choose?"
 }
}